fluentiter/__init__.py
fluentiter/core.py
fluentiter/exceptions.py
fluentiter/itertypes.py
fluentiter/more.py
fluentiter/py.typed
fluentiter-1.2.1.dist-info/LICENSE
fluentiter-1.2.1.dist-info/METADATA
fluentiter-1.2.1.dist-info/WHEEL
fluentiter-1.2.1.dist-info/RECORD
