Metadata-Version: 2.1
Name: fluentiter
Version: 1.2.1
Summary: Nice and clean iterator patterns for python
Home-page: https://github.com/damiondoesthings/fluentiter
Author: Damion Werner
Author-email: damion.werner@gmail.com
Requires-Python: >=3.8,<4.0
Classifier: Programming Language :: Python :: 3
Classifier: Programming Language :: Python :: 3.8
Classifier: Programming Language :: Python :: 3.9
Classifier: Programming Language :: Python :: 3.10
Classifier: Programming Language :: Python :: 3.11
Classifier: Programming Language :: Python :: 3.12
Provides-Extra: more
Requires-Dist: more-itertools (>=10.1.0,<11.0.0) ; extra == "more"
Project-URL: Documentation, https://damiondoesthings.github.io/fluentiter/
Project-URL: Repository, https://github.com/damiondoesthings/fluentiter
